baicaoyuan/__init__.py
baicaoyuan/cmd.py
baicaoyuan/config.yml
baicaoyuan/context.py
baicaoyuan/ghost.py
baicaoyuan/logger.py
baicaoyuan/meta_yaml.py
baicaoyuan/model.py
baicaoyuan/options.py
baicaoyuan/reader.py
baicaoyuan/site.py
baicaoyuan/template.py
baicaoyuan/utils.py
baicaoyuan/writer.py
baicaoyuan/themes/default/archive.html
baicaoyuan/themes/default/base.html
baicaoyuan/themes/default/comment.html
baicaoyuan/themes/default/css_base.html
baicaoyuan/themes/default/footer.html
baicaoyuan/themes/default/google_analytics.html
baicaoyuan/themes/default/index.html
baicaoyuan/themes/default/post.html
baicaoyuan/themes/default/tag.html
baicaoyuan/themes/default/assets/css/code.css
baicaoyuan/themes/default/assets/img/bg.jpg
baicaoyuan/themes/default/assets/img/default.png
baicaoyuan/themes/default/assets/img/down.gif
baicaoyuan/themes/default/assets/img/favicon.ico
baicaoyuan/themes/default/assets/img/up.gif
baicaoyuan/themes/default/assets/js/bs-custom-file-input.js
baicaoyuan/themes/default/assets/js/clipboard.js
baicaoyuan/themes/default/assets/js/highlight-lines.js
baicaoyuan/themes/default/assets/js/highlight.js
baicaoyuan/themes/default/assets/js/jquery-3.5.1.min.js
baicaoyuan/themes/default/assets/js/token.js
baicaoyuan-1.0.1.dist-info/METADATA
baicaoyuan-1.0.1.dist-info/WHEEL
baicaoyuan-1.0.1.dist-info/entry_points.txt
baicaoyuan-1.0.1.dist-info/top_level.txt
baicaoyuan-1.0.1.dist-info/RECORD
