Metadata-Version: 2.1
Name: baicaoyuan
Version: 1.0.1
Summary: A community version of baicaoyuan
Home-page: https://bcy.hello8693.xyz/
Author: hello8693
Author-email: hello8693@hello8693.xyz
License: AGPL 3.0
Keywords: dsz baicaoyuan bcy dianshizhu tvzhu
Classifier: Programming Language :: Python :: 3
Classifier: Intended Audience :: Developers
Classifier: Development Status :: 5 - Production/Stable
Classifier: Topic :: Utilities
Requires-Python: >=3
Requires-Dist: Jinja2
Requires-Dist: Markdown
Requires-Dist: Pygments
Requires-Dist: PyYAML
Requires-Dist: docopt
Requires-Dist: requests
